client/__init__.py
client/run_client.py
client/client/__init__.py
client/client/add_contact.py
client/client/add_menu_corners_radius.py
client/client/del_contact.py
client/client/main_window.py
client/client/main_window_config.py
client/client/start_dialog.py
client/client/transport.py
client/common/__init__.py
client/common/decorators.py
client/common/descriptor.py
client/common/errors.py
client/common/meta.py
client/common/utils.py
client/common/variables.py
client/common/img/arrow_down.png
client/common/img/arrow_up.png
client/common/img/exit.png
client/common/img/history.png
client/common/img/img.jpg
client/common/img/msg_clear.png
client/common/img/msg_send.png
client/common/img/preferences.png
client/common/img/refresh.png
client/common/img/refresh_2.png
client/common/img/search_folder.png
client/common/img/search_folder_2.png
client/common/img/search_icon.png
client/common/img/user_add.png
client/common/img/user_remove.png
client/common/qss/__init__.py
client/common/qss/animated_close_btn.py
client/common/qss/style.py
client/db/__init__.py
client/db/client_db_config.py
client/db/server_db_config.py
client/logs/__init__.py
client/logs/client_log_config.py
client/logs/server_log_config.py
client/unit_tests/__init__.py
client/unit_tests/test_client.py
client/unit_tests/test_server.py
client/unit_tests/test_utils.py
first_ego_mess_client-0.1.3.dist-info/METADATA
first_ego_mess_client-0.1.3.dist-info/WHEEL
first_ego_mess_client-0.1.3.dist-info/top_level.txt
first_ego_mess_client-0.1.3.dist-info/RECORD
